adeptus_administratum/__init__.py
adeptus_administratum/__main__.py
adeptus_administratum/greetings.py
adeptus_administratum/py.typed
adeptus_administratum-0.1.3.dist-info/METADATA
adeptus_administratum-0.1.3.dist-info/WHEEL
adeptus_administratum-0.1.3.dist-info/entry_points.txt
adeptus_administratum-0.1.3.dist-info/licenses/AUTHORS.rst
adeptus_administratum-0.1.3.dist-info/licenses/LICENCE
adeptus_administratum-0.1.3.dist-info/RECORD
