Metadata-Version: 2.4
Name: adeptus-administratum
Version: 0.1.3
Summary: CLI game in 40k setting.
Project-URL: Bug Tracker, https://gitlab.com/swepy/packages/40k-cli/-/issues
Project-URL: Homepage, https://gitlab.com/swepy/packages/40k-cli
Author-email: Dorian Turba <commit.9wuzh@slmail.me>
License-File: AUTHORS.rst
License-File: LICENCE
Classifier: Development Status :: 3 - Alpha
Classifier: License :: OSI Approved :: MIT License
Classifier: Operating System :: OS Independent
Classifier: Programming Language :: Python :: 3
Classifier: Programming Language :: Python :: 3.13
Classifier: Typing :: Typed
Requires-Python: >=3.13
Requires-Dist: rich>=14.1.0
Requires-Dist: typer>=0.16.0
